cv_doc_chunker/__init__.py
cv_doc_chunker/box_processing.py
cv_doc_chunker/config.py
cv_doc_chunker/image_processing.py
cv_doc_chunker/main.py
cv_doc_chunker/models.py
cv_doc_chunker/pdf.py
cv_doc_chunker-0.2.2.dist-info/licenses/LICENSE
cv_doc_chunker-0.2.2.dist-info/METADATA
cv_doc_chunker-0.2.2.dist-info/WHEEL
cv_doc_chunker-0.2.2.dist-info/top_level.txt
cv_doc_chunker-0.2.2.dist-info/RECORD
