Metadata-Version: 2.4
Name: cv-doc-chunker
Version: 0.2.2
Summary: A tool for parsing PDF document layouts and chunking content.
Home-page: https://github.com/Neo-License/cv_doc_chunker
Author: Vahan Martirosyan / Kiwi Data
Author-email: vahan@kiwidata.com
License: MIT
Keywords: pdf,ocr,parsing,document analysis,layout detection,chunking,cv
Classifier: Development Status :: 3 - Alpha
Classifier: Intended Audience :: Developers
Classifier: Intended Audience :: Science/Research
Classifier: Operating System :: OS Independent
Classifier: Programming Language :: Python :: 3
Classifier: Programming Language :: Python :: 3.8
Classifier: Programming Language :: Python :: 3.9
Classifier: Programming Language :: Python :: 3.10
Classifier: Programming Language :: Python :: 3.11
Classifier: Topic :: Scientific/Engineering :: Image Recognition
Classifier: Topic :: Text Processing :: Indexing
Requires-Python: >=3.10
License-File: LICENSE
Requires-Dist: pymupdf==1.25.3
Requires-Dist: PyPDF2==3.0.1
Requires-Dist: doclayout-yolo==0.0.3
Requires-Dist: pdf2image==1.17.0
Requires-Dist: opencv-python==4.11.0.86
Requires-Dist: huggingface_hub==0.28.1
Requires-Dist: tqdm==4.67.1
Requires-Dist: pillow==11.1.0
Requires-Dist: numpy==1.26.4
Requires-Dist: click==8.1.8
Requires-Dist: python-dotenv==1.0.1
Requires-Dist: azure-ai-documentintelligence==1.0.2
Requires-Dist: azure-core==1.33.0
Requires-Dist: pytesseract>=0.3.10
Dynamic: author
Dynamic: author-email
Dynamic: classifier
Dynamic: description
Dynamic: description-content-type
Dynamic: home-page
Dynamic: keywords
Dynamic: license
Dynamic: license-file
Dynamic: requires-dist
Dynamic: requires-python
Dynamic: summary
